eigpca/__init__.py
eigpca-0.1.0.dist-info/LICENSE
eigpca-0.1.0.dist-info/WHEEL
eigpca-0.1.0.dist-info/METADATA
eigpca-0.1.0.dist-info/RECORD
